{"code": "03156", "nom": "Lusigny", "departement": "03", "region": "84", "epci": "200071140", "surface_ha": 4474.261, "foret": {"surface_ha": 946.029, "taux_boisement": 21.144, "score": "C", "score_boisement": "C", "score_coupes": "C"}, "perturbations": {"total_ha": 27.79, "total_pixels": 2779, "pixel_area_ha": 0.01, "perturb_ha_annuel": 3.586, "taux_coupe_annuel": 0.379, "observation_years": 7.75, "par_annee": {"2022": 393, "2023": 1557, "2024": 166, "2025": 663}, "annee_min": 2022, "annee_max": 2025}, "raster": {"xmin": 731319.6885419291, "xmax": 741999.6885419291, "ymin": 6604306.697153928, "ymax": 6612176.697153928, "width": 1068, "height": 787, "pixel_w": 9.99999999999999, "pixel_h": 10.0}, "overlaps_zones_protegees": {"znieff1": {"overlap_pixels": 0, "overlap_ha": 0.0, "zone_pixels": 8092, "zone_ha": 80.92, "zone_in_commune": true}, "znieff2": {"overlap_pixels": 2779, "overlap_ha": 27.79, "zone_pixels": 840516, "zone_ha": 8405.16, "zone_in_commune": true}, "natura_sic": {"overlap_pixels": 0, "overlap_ha": 0.0, "zone_pixels": 9440, "zone_ha": 94.4, "zone_in_commune": true}, "natura_zps": {"overlap_pixels": 388, "overlap_ha": 3.88, "zone_pixels": 214139, "zone_ha": 2141.39, "zone_in_commune": true}, "reserves_naturelles": {"overlap_pixels": 0, "overlap_ha": 0.0, "zone_pixels": 0, "zone_ha": 0.0, "zone_in_commune": false}}, "overlap_foret": {"perturb_in_forest_pixels": 2629, "perturb_in_forest_ha": 26.29, "perturb_outside_forest_pixels": 150, "perturb_outside_forest_ha": 1.5}, "overlap_bdforet": {"bdforet_total_ha": 2121.17, "bdforet_par_type": {"Forêt fermée feuillus": {"pixels": 183259, "ha": 1832.59, "perturb_pixels": 2619, "perturb_ha": 26.19}, "Peupleraie": {"pixels": 3261, "ha": 32.61, "perturb_pixels": 0, "perturb_ha": 0.0}, "Forêt fermée conifères": {"pixels": 15166, "ha": 151.66, "perturb_pixels": 25, "perturb_ha": 0.25}, "Forêt fermée mixte": {"pixels": 5005, "ha": 50.05, "perturb_pixels": 0, "perturb_ha": 0.0}, "Lande": {"pixels": 3833, "ha": 38.33, "perturb_pixels": 0, "perturb_ha": 0.0}, "Formation herbacée": {"pixels": 1290, "ha": 12.9, "perturb_pixels": 0, "perturb_ha": 0.0}, "Forêt ouverte feuillus": {"pixels": 303, "ha": 3.03, "perturb_pixels": 0, "perturb_ha": 0.0}}, "perturb_in_bdforet_pixels": 2644, "perturb_in_bdforet_ha": 26.44}}