{"code": "05120", "nom": "", "departement": "", "region": "", "epci": "", "surface_ha": 8326.318, "foret": {"surface_ha": 5579.109, "taux_boisement": 67.006, "score": "E", "score_boisement": "A", "score_coupes": "E"}, "perturbations": {"total_ha": 15254.68, "total_pixels": 1525468, "pixel_area_ha": 0.01, "perturb_ha_annuel": 1968.346, "taux_coupe_annuel": 35.281, "observation_years": 7.75, "par_annee": {"-2145484": 1525468}, "annee_min": -2145484, "annee_max": -2145484}, "raster": {"xmin": 1010289.6885419288, "xmax": 1022959.6885419288, "ymin": 6406136.697153928, "ymax": 6418176.697153928, "width": 1267, "height": 1204, "pixel_w": 10.0, "pixel_h": 10.0}, "overlaps_zones_protegees": {"znieff1": {"overlap_pixels": 720353, "overlap_ha": 7203.53, "zone_pixels": 720353, "zone_ha": 7203.53, "zone_in_commune": true}, "znieff2": {"overlap_pixels": 1073113, "overlap_ha": 10731.13, "zone_pixels": 1073113, "zone_ha": 10731.13, "zone_in_commune": true}, "natura_sic": {"overlap_pixels": 822331, "overlap_ha": 8223.31, "zone_pixels": 822331, "zone_ha": 8223.31, "zone_in_commune": true}, "natura_zps": {"overlap_pixels": 635728, "overlap_ha": 6357.28, "zone_pixels": 635728, "zone_ha": 6357.28, "zone_in_commune": true}, "reserves_naturelles": {"overlap_pixels": 0, "overlap_ha": 0.0, "zone_pixels": 0, "zone_ha": 0.0, "zone_in_commune": false}}, "overlap_foret": {"perturb_in_forest_pixels": 291302, "perturb_in_forest_ha": 2913.02, "perturb_outside_forest_pixels": 1234166, "perturb_outside_forest_ha": 12341.66}, "overlap_bdforet": {"bdforet_total_ha": 7385.87, "bdforet_par_type": {"Formation herbacée": {"pixels": 388431, "ha": 3884.31, "perturb_pixels": 388431, "perturb_ha": 3884.31}, "Lande": {"pixels": 89627, "ha": 896.27, "perturb_pixels": 89627, "perturb_ha": 896.27}, "Forêt ouverte conifères": {"pixels": 77604, "ha": 776.04, "perturb_pixels": 77604, "perturb_ha": 776.04}, "Forêt fermée conifères": {"pixels": 166368, "ha": 1663.68, "perturb_pixels": 166368, "perturb_ha": 1663.68}, "Forêt fermée sans couvert arboré": {"pixels": 8361, "ha": 83.61, "perturb_pixels": 8361, "perturb_ha": 83.61}, "Forêt ouverte sans couvert arboré": {"pixels": 6212, "ha": 62.12, "perturb_pixels": 6212, "perturb_ha": 62.12}, "Forêt fermée mixte": {"pixels": 1984, "ha": 19.84, "perturb_pixels": 1984, "perturb_ha": 19.84}}, "perturb_in_bdforet_pixels": 738587, "perturb_in_bdforet_ha": 7385.87}}