{"code": "11101", "nom": "Coudons", "departement": "11", "region": "76", "epci": "200043776", "surface_ha": 972.733, "foret": {"surface_ha": 854.454, "taux_boisement": 87.84, "score": "B", "score_boisement": "A", "score_coupes": "B"}, "perturbations": {"total_ha": 9.41, "total_pixels": 941, "pixel_area_ha": 0.01, "perturb_ha_annuel": 1.214, "taux_coupe_annuel": 0.142, "observation_years": 7.75, "par_annee": {"2019": 274, "2020": 47, "2023": 221, "2024": 373, "2025": 26}, "annee_min": 2019, "annee_max": 2025}, "raster": {"xmin": 625589.6885419292, "xmax": 630719.6885419292, "ymin": 6194586.697153928, "ymax": 6198276.697153928, "width": 513, "height": 369, "pixel_w": 9.99999999999999, "pixel_h": 10.0}, "overlaps_zones_protegees": {"znieff1": {"overlap_pixels": 0, "overlap_ha": 0.0, "zone_pixels": 0, "zone_ha": 0.0, "zone_in_commune": false}, "znieff2": {"overlap_pixels": 941, "overlap_ha": 9.41, "zone_pixels": 189297, "zone_ha": 1892.97, "zone_in_commune": true}, "natura_sic": {"overlap_pixels": 0, "overlap_ha": 0.0, "zone_pixels": 0, "zone_ha": 0.0, "zone_in_commune": false}, "natura_zps": {"overlap_pixels": 941, "overlap_ha": 9.41, "zone_pixels": 189297, "zone_ha": 1892.97, "zone_in_commune": true}, "reserves_naturelles": {"overlap_pixels": 0, "overlap_ha": 0.0, "zone_pixels": 0, "zone_ha": 0.0, "zone_in_commune": false}}, "overlap_foret": {"perturb_in_forest_pixels": 917, "perturb_in_forest_ha": 9.17, "perturb_outside_forest_pixels": 24, "perturb_outside_forest_ha": 0.24}, "overlap_bdforet": {"bdforet_total_ha": 1723.11, "bdforet_par_type": {"Forêt fermée feuillus": {"pixels": 58095, "ha": 580.95, "perturb_pixels": 41, "perturb_ha": 0.41}, "Forêt fermée conifères": {"pixels": 52307, "ha": 523.07, "perturb_pixels": 598, "perturb_ha": 5.98}, "Forêt fermée mixte": {"pixels": 49445, "ha": 494.45, "perturb_pixels": 266, "perturb_ha": 2.66}, "Forêt ouverte feuillus": {"pixels": 5676, "ha": 56.76, "perturb_pixels": 2, "perturb_ha": 0.02}, "Forêt ouverte mixte": {"pixels": 4267, "ha": 42.67, "perturb_pixels": 0, "perturb_ha": 0.0}, "Forêt fermée sans couvert arboré": {"pixels": 1649, "ha": 16.49, "perturb_pixels": 0, "perturb_ha": 0.0}, "Lande": {"pixels": 872, "ha": 8.72, "perturb_pixels": 0, "perturb_ha": 0.0}}, "perturb_in_bdforet_pixels": 907, "perturb_in_bdforet_ha": 9.07}}