{"code": "22177", "nom": "Pléguien", "departement": "22", "region": "53", "epci": "200069086", "surface_ha": 1570.409, "foret": {"surface_ha": 340.478, "taux_boisement": 21.681, "score": "D", "score_boisement": "C", "score_coupes": "D"}, "perturbations": {"total_ha": 23.1, "total_pixels": 2310, "pixel_area_ha": 0.01, "perturb_ha_annuel": 2.981, "taux_coupe_annuel": 0.875, "observation_years": 7.75, "par_annee": {"2018": 78, "2019": 276, "2020": 690, "2021": 63, "2022": 346, "2023": 414, "2024": 96, "2025": 347}, "annee_min": 2018, "annee_max": 2025}, "raster": {"xmin": 259429.6885419296, "xmax": 264239.6885419296, "ymin": 6851096.697153928, "ymax": 6856526.697153928, "width": 481, "height": 543, "pixel_w": 9.99999999999999, "pixel_h": 10.0}, "overlaps_zones_protegees": {"znieff1": {"overlap_pixels": 0, "overlap_ha": 0.0, "zone_pixels": 0, "zone_ha": 0.0, "zone_in_commune": false}, "znieff2": {"overlap_pixels": 3, "overlap_ha": 0.03, "zone_pixels": 15107, "zone_ha": 151.07, "zone_in_commune": true}, "natura_sic": {"overlap_pixels": 0, "overlap_ha": 0.0, "zone_pixels": 0, "zone_ha": 0.0, "zone_in_commune": false}, "natura_zps": {"overlap_pixels": 0, "overlap_ha": 0.0, "zone_pixels": 0, "zone_ha": 0.0, "zone_in_commune": false}, "reserves_naturelles": {"overlap_pixels": 0, "overlap_ha": 0.0, "zone_pixels": 0, "zone_ha": 0.0, "zone_in_commune": false}}, "overlap_foret": {"perturb_in_forest_pixels": 1906, "perturb_in_forest_ha": 19.06, "perturb_outside_forest_pixels": 404, "perturb_outside_forest_ha": 4.04}, "overlap_bdforet": {"bdforet_total_ha": 737.37, "bdforet_par_type": {"Forêt fermée feuillus": {"pixels": 55238, "ha": 552.38, "perturb_pixels": 738, "perturb_ha": 7.38}, "Peupleraie": {"pixels": 7171, "ha": 71.71, "perturb_pixels": 910, "perturb_ha": 9.1}, "Forêt fermée conifères": {"pixels": 2475, "ha": 24.75, "perturb_pixels": 371, "perturb_ha": 3.71}, "Forêt ouverte feuillus": {"pixels": 902, "ha": 9.02, "perturb_pixels": 5, "perturb_ha": 0.05}, "Forêt fermée sans couvert arboré": {"pixels": 1190, "ha": 11.9, "perturb_pixels": 1, "perturb_ha": 0.01}, "Lande": {"pixels": 1265, "ha": 12.65, "perturb_pixels": 0, "perturb_ha": 0.0}, "Forêt fermée mixte": {"pixels": 5496, "ha": 54.96, "perturb_pixels": 181, "perturb_ha": 1.81}}, "perturb_in_bdforet_pixels": 2206, "perturb_in_bdforet_ha": 22.06}}