{"code": "34222", "nom": "Puilacher", "departement": "34", "region": "76", "epci": "243400694", "surface_ha": 269.876, "foret": {"surface_ha": 18.058, "taux_boisement": 6.691, "score": "E", "score_boisement": "E", "score_coupes": "A"}, "perturbations": {"total_ha": 0.0, "total_pixels": 0, "pixel_area_ha": 0.01, "perturb_ha_annuel": 0.0, "taux_coupe_annuel": 0.0, "observation_years": 7.75, "par_annee": {}, "annee_min": null, "annee_max": null}, "raster": {"xmin": 739439.6885419291, "xmax": 741949.6885419291, "ymin": 6273076.697153928, "ymax": 6275286.697153928, "width": 251, "height": 221, "pixel_w": 9.99999999999999, "pixel_h": 10.0}, "overlaps_zones_protegees": {"znieff1": {"overlap_pixels": 0, "overlap_ha": 0.0, "zone_pixels": 0, "zone_ha": 0.0, "zone_in_commune": false}, "znieff2": {"overlap_pixels": 0, "overlap_ha": 0.0, "zone_pixels": 0, "zone_ha": 0.0, "zone_in_commune": false}, "natura_sic": {"overlap_pixels": 0, "overlap_ha": 0.0, "zone_pixels": 0, "zone_ha": 0.0, "zone_in_commune": false}, "natura_zps": {"overlap_pixels": 0, "overlap_ha": 0.0, "zone_pixels": 0, "zone_ha": 0.0, "zone_in_commune": false}, "reserves_naturelles": {"overlap_pixels": 0, "overlap_ha": 0.0, "zone_pixels": 0, "zone_ha": 0.0, "zone_in_commune": false}}, "overlap_foret": {"perturb_in_forest_pixels": 0, "perturb_in_forest_ha": 0.0, "perturb_outside_forest_pixels": 0, "perturb_outside_forest_ha": 0.0}, "overlap_bdforet": {"bdforet_total_ha": 45.45, "bdforet_par_type": {"Lande": {"pixels": 2276, "ha": 22.76, "perturb_pixels": 0, "perturb_ha": 0.0}, "Forêt fermée feuillus": {"pixels": 1245, "ha": 12.45, "perturb_pixels": 0, "perturb_ha": 0.0}, "Forêt ouverte conifères": {"pixels": 69, "ha": 0.69, "perturb_pixels": 0, "perturb_ha": 0.0}, "Forêt fermée mixte": {"pixels": 660, "ha": 6.6, "perturb_pixels": 0, "perturb_ha": 0.0}, "Forêt ouverte feuillus": {"pixels": 295, "ha": 2.95, "perturb_pixels": 0, "perturb_ha": 0.0}}, "perturb_in_bdforet_pixels": 0, "perturb_in_bdforet_ha": 0.0}}