{"code": "52034", "nom": "Bailly-aux-Forges", "departement": "52", "region": "44", "epci": "200068666", "surface_ha": 1068.133, "foret": {"surface_ha": 851.006, "taux_boisement": 79.672, "score": "A", "score_boisement": "A", "score_coupes": "A"}, "perturbations": {"total_ha": 4.37, "total_pixels": 437, "pixel_area_ha": 0.01, "perturb_ha_annuel": 0.564, "taux_coupe_annuel": 0.066, "observation_years": 7.75, "par_annee": {"2018": 196, "2019": 64, "2020": 50, "2023": 127}, "annee_min": 2018, "annee_max": 2023}, "raster": {"xmin": 838289.688541929, "xmax": 843619.688541929, "ymin": 6816536.697153928, "ymax": 6821336.697153928, "width": 533, "height": 480, "pixel_w": 9.99999999999999, "pixel_h": 10.0}, "overlaps_zones_protegees": {"znieff1": {"overlap_pixels": 0, "overlap_ha": 0.0, "zone_pixels": 0, "zone_ha": 0.0, "zone_in_commune": false}, "znieff2": {"overlap_pixels": 0, "overlap_ha": 0.0, "zone_pixels": 0, "zone_ha": 0.0, "zone_in_commune": false}, "natura_sic": {"overlap_pixels": 0, "overlap_ha": 0.0, "zone_pixels": 0, "zone_ha": 0.0, "zone_in_commune": false}, "natura_zps": {"overlap_pixels": 0, "overlap_ha": 0.0, "zone_pixels": 0, "zone_ha": 0.0, "zone_in_commune": false}, "reserves_naturelles": {"overlap_pixels": 0, "overlap_ha": 0.0, "zone_pixels": 0, "zone_ha": 0.0, "zone_in_commune": false}}, "overlap_foret": {"perturb_in_forest_pixels": 436, "perturb_in_forest_ha": 4.36, "perturb_outside_forest_pixels": 1, "perturb_outside_forest_ha": 0.01}, "overlap_bdforet": {"bdforet_total_ha": 2189.52, "bdforet_par_type": {"Forêt fermée feuillus": {"pixels": 201128, "ha": 2011.28, "perturb_pixels": 202, "perturb_ha": 2.02}, "Forêt fermée sans couvert arboré": {"pixels": 8769, "ha": 87.69, "perturb_pixels": 0, "perturb_ha": 0.0}, "Forêt fermée mixte": {"pixels": 6491, "ha": 64.91, "perturb_pixels": 43, "perturb_ha": 0.43}, "Peupleraie": {"pixels": 957, "ha": 9.57, "perturb_pixels": 0, "perturb_ha": 0.0}, "Forêt fermée conifères": {"pixels": 1607, "ha": 16.07, "perturb_pixels": 192, "perturb_ha": 1.92}}, "perturb_in_bdforet_pixels": 437, "perturb_in_bdforet_ha": 4.37}}