{"code": "55489", "nom": "Sivry-la-Perche", "departement": "55", "region": "44", "epci": "200049187", "surface_ha": 1218.308, "foret": {"surface_ha": 265.733, "taux_boisement": 21.812, "score": "C", "score_boisement": "C", "score_coupes": "B"}, "perturbations": {"total_ha": 3.45, "total_pixels": 345, "pixel_area_ha": 0.01, "perturb_ha_annuel": 0.445, "taux_coupe_annuel": 0.168, "observation_years": 7.75, "par_annee": {"2019": 177, "2020": 168}, "annee_min": 2019, "annee_max": 2020}, "raster": {"xmin": 862159.688541929, "xmax": 866959.688541929, "ymin": 6893166.697153928, "ymax": 6897776.697153928, "width": 480, "height": 461, "pixel_w": 9.99999999999999, "pixel_h": 10.0}, "overlaps_zones_protegees": {"znieff1": {"overlap_pixels": 0, "overlap_ha": 0.0, "zone_pixels": 8918, "zone_ha": 89.18, "zone_in_commune": true}, "znieff2": {"overlap_pixels": 0, "overlap_ha": 0.0, "zone_pixels": 0, "zone_ha": 0.0, "zone_in_commune": false}, "natura_sic": {"overlap_pixels": 0, "overlap_ha": 0.0, "zone_pixels": 3268, "zone_ha": 32.68, "zone_in_commune": true}, "natura_zps": {"overlap_pixels": 0, "overlap_ha": 0.0, "zone_pixels": 0, "zone_ha": 0.0, "zone_in_commune": false}, "reserves_naturelles": {"overlap_pixels": 0, "overlap_ha": 0.0, "zone_pixels": 0, "zone_ha": 0.0, "zone_in_commune": false}}, "overlap_foret": {"perturb_in_forest_pixels": 345, "perturb_in_forest_ha": 3.45, "perturb_outside_forest_pixels": 0, "perturb_outside_forest_ha": 0.0}, "overlap_bdforet": {"bdforet_total_ha": 529.93, "bdforet_par_type": {"Forêt fermée feuillus": {"pixels": 42881, "ha": 428.81, "perturb_pixels": 33, "perturb_ha": 0.33}, "Forêt fermée mixte": {"pixels": 4335, "ha": 43.35, "perturb_pixels": 0, "perturb_ha": 0.0}, "Forêt fermée conifères": {"pixels": 3537, "ha": 35.37, "perturb_pixels": 312, "perturb_ha": 3.12}, "Forêt fermée sans couvert arboré": {"pixels": 435, "ha": 4.35, "perturb_pixels": 0, "perturb_ha": 0.0}, "Lande": {"pixels": 118, "ha": 1.18, "perturb_pixels": 0, "perturb_ha": 0.0}, "Forêt ouverte feuillus": {"pixels": 419, "ha": 4.19, "perturb_pixels": 0, "perturb_ha": 0.0}, "Forêt ouverte mixte": {"pixels": 1268, "ha": 12.68, "perturb_pixels": 0, "perturb_ha": 0.0}}, "perturb_in_bdforet_pixels": 345, "perturb_in_bdforet_ha": 3.45}}