{"code": "57250", "nom": "Goetzenbruck", "departement": "57", "region": "44", "epci": "200069441", "surface_ha": 759.954, "foret": {"surface_ha": 504.563, "taux_boisement": 66.394, "score": "B", "score_boisement": "A", "score_coupes": "B"}, "perturbations": {"total_ha": 5.33, "total_pixels": 533, "pixel_area_ha": 0.01, "perturb_ha_annuel": 0.688, "taux_coupe_annuel": 0.136, "observation_years": 7.75, "par_annee": {"2020": 49, "2021": 168, "2022": 6, "2024": 289, "2025": 21}, "annee_min": 2020, "annee_max": 2025, "rang_taux_coupe": 21796, "rang_total": 35114, "taux_coupe_national_moyen": 1.181}, "raster": {"xmin": 1018949.6885419288, "xmax": 1022319.6885419288, "ymin": 6881506.697153928, "ymax": 6886326.697153928, "width": 337, "height": 482, "pixel_w": 9.99999999999999, "pixel_h": 10.0}, "overlaps_zones_protegees": {"znieff1": {"overlap_pixels": 257, "overlap_ha": 2.57, "zone_pixels": 39209, "zone_ha": 392.09, "zone_in_commune": true}, "znieff2": {"overlap_pixels": 0, "overlap_ha": 0.0, "zone_pixels": 94967, "zone_ha": 949.67, "zone_in_commune": true}, "natura_sic": {"overlap_pixels": 0, "overlap_ha": 0.0, "zone_pixels": 8635, "zone_ha": 86.35, "zone_in_commune": true}, "natura_zps": {"overlap_pixels": 0, "overlap_ha": 0.0, "zone_pixels": 0, "zone_ha": 0.0, "zone_in_commune": false}, "reserves_naturelles": {"overlap_pixels": 0, "overlap_ha": 0.0, "zone_pixels": 0, "zone_ha": 0.0, "zone_in_commune": false}}, "overlap_foret": {"perturb_in_forest_pixels": 323, "perturb_in_forest_ha": 3.23, "perturb_outside_forest_pixels": 210, "perturb_outside_forest_ha": 2.1}, "overlap_bdforet": {"bdforet_total_ha": 1262.77, "par_couvert": {"Forêt fermée": {"ha": 1251.08, "perturb_ha": 4.84}, "Forêt ouverte": {"ha": 1.98, "perturb_ha": 0.0}, "Lande/herbacée": {"ha": 9.71, "perturb_ha": 0.0}}, "par_type": {"Formation herbacée": {"ha": 3.72, "perturb_ha": 0.0}, "Forêt fermée conifères": {"ha": 195.55, "perturb_ha": 3.91}, "Forêt fermée feuillus": {"ha": 772.13, "perturb_ha": 0.36}, "Forêt fermée mixte": {"ha": 273.11, "perturb_ha": 0.57}, "Forêt fermée sans couvert arboré": {"ha": 10.29, "perturb_ha": 0.0}, "Forêt ouverte feuillus": {"ha": 0.9, "perturb_ha": 0.0}, "Forêt ouverte mixte": {"ha": 1.08, "perturb_ha": 0.0}, "Lande": {"ha": 5.99, "perturb_ha": 0.0}}, "par_essence": {"Formation herbacée": {"ha": 3.72, "perturb_ha": 0.0}, "Forêt fermée de chênes décidus purs": {"ha": 98.71, "perturb_ha": 0.0}, "Forêt fermée de douglas pur": {"ha": 16.66, "perturb_ha": 0.0}, "Forêt fermée de feuillus purs en îlots": {"ha": 1.27, "perturb_ha": 0.0}, "Forêt fermée de hêtre pur": {"ha": 234.25, "perturb_ha": 0.03}, "Forêt fermée de mélèze pur": {"ha": 2.11, "perturb_ha": 0.0}, "Forêt fermée de pin sylvestre pur": {"ha": 59.9, "perturb_ha": 0.0}, "Forêt fermée de sapin ou épicéa": {"ha": 22.82, "perturb_ha": 1.22}, "Forêt fermée dun autre conifère pur autre que pin ": {"ha": 71.15, "perturb_ha": 2.34}, "Forêt fermée sans couvert arboré": {"ha": 10.29, "perturb_ha": 0.0}, "Forêt fermée à mélange de conifères": {"ha": 22.91, "perturb_ha": 0.35}, "Forêt fermée à mélange de conifères prépondérants et feuillus": {"ha": 162.2, "perturb_ha": 0.57}, "Forêt fermée à mélange de feuillus": {"ha": 437.9, "perturb_ha": 0.33}, "Forêt fermée à mélange de feuillus prépondérants et conifères": {"ha": 110.91, "perturb_ha": 0.0}, "Forêt ouverte de feuillus purs": {"ha": 0.9, "perturb_ha": 0.0}, "Forêt ouverte à mélange de feuillus et conifères": {"ha": 1.08, "perturb_ha": 0.0}, "Lande": {"ha": 5.99, "perturb_ha": 0.0}}, "perturb_in_bdforet_ha": 4.84}, "population": {"population": 1444, "densite_hab_km2": 190.0}, "forets_anciennes": {"surface_ha": 558.64, "taux_foret_ancienne": 73.495, "perturb_in_ancienne_ha": 4.84, "perturb_in_ancienne_pct": 90.807, "par_nature": {"foret ancienne": {"ha": 419.77, "perturb_ha": 0.99}, "foret disparue": {"ha": 55.27, "perturb_ha": 0.0}, "foret recente": {"ha": 83.6, "perturb_ha": 3.85}}}}