{"code": "60119", "nom": "Cambronne-lès-Ribécourt", "departement": "60", "region": "32", "epci": "246000772", "surface_ha": 697.523, "foret": {"surface_ha": 249.265, "taux_boisement": 35.736, "score": "D", "score_boisement": "C", "score_coupes": "D"}, "perturbations": {"total_ha": 17.18, "total_pixels": 1718, "pixel_area_ha": 0.01, "perturb_ha_annuel": 2.217, "taux_coupe_annuel": 0.889, "observation_years": 7.75, "par_annee": {"2018": 54, "2019": 549, "2020": 4, "2022": 860, "2023": 16, "2024": 220, "2025": 15}, "annee_min": 2018, "annee_max": 2025}, "raster": {"xmin": 691359.6885419291, "xmax": 694659.6885419291, "ymin": 6931656.697153928, "ymax": 6936686.697153928, "width": 330, "height": 503, "pixel_w": 9.99999999999999, "pixel_h": 10.0}, "overlaps_zones_protegees": {"znieff1": {"overlap_pixels": 603, "overlap_ha": 6.03, "zone_pixels": 81909, "zone_ha": 819.09, "zone_in_commune": true}, "znieff2": {"overlap_pixels": 370, "overlap_ha": 3.7, "zone_pixels": 14882, "zone_ha": 148.82, "zone_in_commune": true}, "natura_sic": {"overlap_pixels": 0, "overlap_ha": 0.0, "zone_pixels": 0, "zone_ha": 0.0, "zone_in_commune": false}, "natura_zps": {"overlap_pixels": 851, "overlap_ha": 8.51, "zone_pixels": 27070, "zone_ha": 270.7, "zone_in_commune": true}, "reserves_naturelles": {"overlap_pixels": 0, "overlap_ha": 0.0, "zone_pixels": 0, "zone_ha": 0.0, "zone_in_commune": false}}, "overlap_foret": {"perturb_in_forest_pixels": 1401, "perturb_in_forest_ha": 14.01, "perturb_outside_forest_pixels": 317, "perturb_outside_forest_ha": 3.17}, "overlap_bdforet": {"bdforet_total_ha": 701.56, "bdforet_par_type": {"Forêt fermée feuillus": {"pixels": 63284, "ha": 632.84, "perturb_pixels": 855, "perturb_ha": 8.55}, "Peupleraie": {"pixels": 6596, "ha": 65.96, "perturb_pixels": 626, "perturb_ha": 6.26}, "Lande": {"pixels": 78, "ha": 0.78, "perturb_pixels": 0, "perturb_ha": 0.0}, "Forêt fermée conifères": {"pixels": 16, "ha": 0.16, "perturb_pixels": 0, "perturb_ha": 0.0}, "Forêt fermée mixte": {"pixels": 182, "ha": 1.82, "perturb_pixels": 0, "perturb_ha": 0.0}}, "perturb_in_bdforet_pixels": 1481, "perturb_in_bdforet_ha": 14.81}}