{"code": "62206", "nom": "Campigneulles-les-Grandes", "departement": "62", "region": "32", "epci": "200069029", "surface_ha": 542.008, "foret": {"surface_ha": 78.39, "taux_boisement": 14.463, "score": "D", "score_boisement": "D", "score_coupes": "C"}, "perturbations": {"total_ha": 1.73, "total_pixels": 173, "pixel_area_ha": 0.01, "perturb_ha_annuel": 0.223, "taux_coupe_annuel": 0.285, "observation_years": 7.75, "par_annee": {"2019": 46, "2020": 86, "2024": 41}, "annee_min": 2019, "annee_max": 2024}, "raster": {"xmin": 606619.6885419292, "xmax": 609349.6885419292, "ymin": 7036336.697153928, "ymax": 7039586.697153928, "width": 273, "height": 325, "pixel_w": 9.99999999999999, "pixel_h": 10.0}, "overlaps_zones_protegees": {"znieff1": {"overlap_pixels": 0, "overlap_ha": 0.0, "zone_pixels": 0, "zone_ha": 0.0, "zone_in_commune": false}, "znieff2": {"overlap_pixels": 0, "overlap_ha": 0.0, "zone_pixels": 0, "zone_ha": 0.0, "zone_in_commune": false}, "natura_sic": {"overlap_pixels": 0, "overlap_ha": 0.0, "zone_pixels": 0, "zone_ha": 0.0, "zone_in_commune": false}, "natura_zps": {"overlap_pixels": 0, "overlap_ha": 0.0, "zone_pixels": 0, "zone_ha": 0.0, "zone_in_commune": false}, "reserves_naturelles": {"overlap_pixels": 0, "overlap_ha": 0.0, "zone_pixels": 0, "zone_ha": 0.0, "zone_in_commune": false}}, "overlap_foret": {"perturb_in_forest_pixels": 41, "perturb_in_forest_ha": 0.41, "perturb_outside_forest_pixels": 132, "perturb_outside_forest_ha": 1.32}, "overlap_bdforet": {"bdforet_total_ha": 96.31, "par_couvert": {"Forêt fermée": {"ha": 93.72, "perturb_ha": 0.41}, "Forêt ouverte": {"ha": 0.69, "perturb_ha": 0.0}, "Lande/herbacée": {"ha": 0.99, "perturb_ha": 0.0}, "Peupleraie": {"ha": 0.91, "perturb_ha": 0.0}}, "par_type": {"Forêt fermée feuillus": {"ha": 93.72, "perturb_ha": 0.41}, "Forêt ouverte feuillus": {"ha": 0.69, "perturb_ha": 0.0}, "Lande": {"ha": 0.99, "perturb_ha": 0.0}, "Peupleraie": {"ha": 0.91, "perturb_ha": 0.0}}, "par_essence": {"Forêt fermée de feuillus purs en îlots": {"ha": 8.2, "perturb_ha": 0.0}, "Forêt fermée dun autre feuillu pur": {"ha": 2.6, "perturb_ha": 0.0}, "Forêt fermée à mélange de feuillus": {"ha": 82.92, "perturb_ha": 0.41}, "Forêt ouverte de feuillus purs": {"ha": 0.69, "perturb_ha": 0.0}, "Lande": {"ha": 0.99, "perturb_ha": 0.0}, "Peupleraie": {"ha": 0.91, "perturb_ha": 0.0}}, "perturb_in_bdforet_ha": 0.41}, "population": {"population": 281, "densite_hab_km2": 51.8}, "forets_anciennes": {"surface_ha": 91.22, "taux_foret_ancienne": 16.939, "perturb_in_ancienne_ha": 0.41, "perturb_in_ancienne_pct": 23.699, "par_nature": {"foret ancienne": {"ha": 54.08, "perturb_ha": 0.41}, "foret disparue": {"ha": 12.27, "perturb_ha": 0.0}, "foret recente": {"ha": 24.87, "perturb_ha": 0.0}}}}