{"code": "65137", "nom": "Caussade-Rivière", "departement": "65", "region": "76", "epci": "200072106", "surface_ha": 623.034, "foret": {"surface_ha": 108.446, "taux_boisement": 17.406, "score": "D", "score_boisement": "D", "score_coupes": "D"}, "perturbations": {"total_ha": 7.21, "total_pixels": 721, "pixel_area_ha": 0.01, "perturb_ha_annuel": 0.93, "taux_coupe_annuel": 0.858, "observation_years": 7.75, "par_annee": {"2019": 22, "2020": 121, "2022": 539, "2023": 1, "2024": 38}, "annee_min": 2019, "annee_max": 2024}, "raster": {"xmin": 456339.6885419294, "xmax": 460269.6885419294, "ymin": 6271656.697153928, "ymax": 6275106.697153928, "width": 393, "height": 345, "pixel_w": 9.99999999999999, "pixel_h": 10.0}, "overlaps_zones_protegees": {"znieff1": {"overlap_pixels": 0, "overlap_ha": 0.0, "zone_pixels": 9924, "zone_ha": 99.24, "zone_in_commune": true}, "znieff2": {"overlap_pixels": 7, "overlap_ha": 0.07, "zone_pixels": 15120, "zone_ha": 151.2, "zone_in_commune": true}, "natura_sic": {"overlap_pixels": 2, "overlap_ha": 0.02, "zone_pixels": 11064, "zone_ha": 110.64, "zone_in_commune": true}, "natura_zps": {"overlap_pixels": 0, "overlap_ha": 0.0, "zone_pixels": 0, "zone_ha": 0.0, "zone_in_commune": false}, "reserves_naturelles": {"overlap_pixels": 0, "overlap_ha": 0.0, "zone_pixels": 0, "zone_ha": 0.0, "zone_in_commune": false}}, "overlap_foret": {"perturb_in_forest_pixels": 659, "perturb_in_forest_ha": 6.59, "perturb_outside_forest_pixels": 62, "perturb_outside_forest_ha": 0.62}, "overlap_bdforet": {"bdforet_total_ha": 310.67, "bdforet_par_type": {"Forêt fermée feuillus": {"pixels": 22348, "ha": 223.48, "perturb_pixels": 139, "perturb_ha": 1.39}, "Peupleraie": {"pixels": 8268, "ha": 82.68, "perturb_pixels": 560, "perturb_ha": 5.6}, "Formation herbacée": {"pixels": 389, "ha": 3.89, "perturb_pixels": 0, "perturb_ha": 0.0}, "Lande": {"pixels": 62, "ha": 0.62, "perturb_pixels": 0, "perturb_ha": 0.0}}, "perturb_in_bdforet_pixels": 699, "perturb_in_bdforet_ha": 6.99}}