{"code": "72200", "nom": "Moncé-en-Belin", "departement": "72", "region": "52", "epci": "247200447", "surface_ha": 1757.194, "foret": {"surface_ha": 602.971, "taux_boisement": 34.314, "score": "D", "score_boisement": "C", "score_coupes": "D"}, "perturbations": {"total_ha": 43.44, "total_pixels": 4344, "pixel_area_ha": 0.01, "perturb_ha_annuel": 5.605, "taux_coupe_annuel": 0.93, "observation_years": 7.75, "par_annee": {"2019": 1048, "2020": 1308, "2021": 489, "2022": 509, "2023": 420, "2024": 229, "2025": 341}, "annee_min": 2019, "annee_max": 2025}, "raster": {"xmin": 487379.68854192935, "xmax": 493619.68854192935, "ymin": 6756006.697153928, "ymax": 6761656.697153928, "width": 624, "height": 565, "pixel_w": 9.99999999999999, "pixel_h": 10.0}, "overlaps_zones_protegees": {"znieff1": {"overlap_pixels": 195, "overlap_ha": 1.95, "zone_pixels": 8009, "zone_ha": 80.09, "zone_in_commune": true}, "znieff2": {"overlap_pixels": 1236, "overlap_ha": 12.36, "zone_pixels": 54579, "zone_ha": 545.79, "zone_in_commune": true}, "natura_sic": {"overlap_pixels": 0, "overlap_ha": 0.0, "zone_pixels": 0, "zone_ha": 0.0, "zone_in_commune": false}, "natura_zps": {"overlap_pixels": 0, "overlap_ha": 0.0, "zone_pixels": 0, "zone_ha": 0.0, "zone_in_commune": false}, "reserves_naturelles": {"overlap_pixels": 0, "overlap_ha": 0.0, "zone_pixels": 0, "zone_ha": 0.0, "zone_in_commune": false}}, "overlap_foret": {"perturb_in_forest_pixels": 3484, "perturb_in_forest_ha": 34.84, "perturb_outside_forest_pixels": 860, "perturb_outside_forest_ha": 8.6}, "overlap_bdforet": {"bdforet_total_ha": 1162.68, "par_couvert": {"Forêt fermée": {"ha": 1076.84, "perturb_ha": 35.79}, "Forêt ouverte": {"ha": 9.59, "perturb_ha": 0.0}, "Lande/herbacée": {"ha": 29.9, "perturb_ha": 0.0}, "Peupleraie": {"ha": 46.35, "perturb_ha": 5.84}}, "par_type": {"Formation herbacée": {"ha": 3.16, "perturb_ha": 0.0}, "Forêt fermée conifères": {"ha": 648.89, "perturb_ha": 25.34}, "Forêt fermée feuillus": {"ha": 295.31, "perturb_ha": 3.64}, "Forêt fermée mixte": {"ha": 66.21, "perturb_ha": 1.38}, "Forêt fermée sans couvert arboré": {"ha": 66.43, "perturb_ha": 5.43}, "Forêt ouverte feuillus": {"ha": 9.59, "perturb_ha": 0.0}, "Lande": {"ha": 26.74, "perturb_ha": 0.0}, "Peupleraie": {"ha": 46.35, "perturb_ha": 5.84}}, "par_essence": {"Formation herbacée": {"ha": 3.16, "perturb_ha": 0.0}, "Forêt fermée de chênes décidus purs": {"ha": 39.92, "perturb_ha": 0.39}, "Forêt fermée de conifères purs en îlots": {"ha": 2.02, "perturb_ha": 0.0}, "Forêt fermée de feuillus purs en îlots": {"ha": 29.73, "perturb_ha": 0.0}, "Forêt fermée de pin laricio ou pin noir pur": {"ha": 18.35, "perturb_ha": 0.0}, "Forêt fermée de pin maritime pur": {"ha": 564.26, "perturb_ha": 25.16}, "Forêt fermée de pin sylvestre pur": {"ha": 21.64, "perturb_ha": 0.0}, "Forêt fermée d’un autre feuillu pur": {"ha": 19.08, "perturb_ha": 1.33}, "Forêt fermée sans couvert arboré": {"ha": 66.43, "perturb_ha": 5.43}, "Forêt fermée à mélange de conifères prépondérants et feuillus": {"ha": 37.37, "perturb_ha": 0.9}, "Forêt fermée à mélange de feuillus": {"ha": 206.58, "perturb_ha": 1.92}, "Forêt fermée à mélange de feuillus prépondérants et conifères": {"ha": 28.84, "perturb_ha": 0.48}, "Forêt fermée à mélange de pins purs": {"ha": 42.62, "perturb_ha": 0.18}, "Forêt ouverte de feuillus purs": {"ha": 9.59, "perturb_ha": 0.0}, "Lande": {"ha": 26.74, "perturb_ha": 0.0}, "Peupleraie": {"ha": 46.35, "perturb_ha": 5.84}}, "perturb_in_bdforet_ha": 41.63}, "population": {"population": 3675, "densite_hab_km2": 209.1}, "forets_anciennes": {"surface_ha": 760.24, "taux_foret_ancienne": 43.313, "perturb_in_ancienne_ha": 41.93, "perturb_in_ancienne_pct": 96.524, "par_nature": {"foret ancienne": {"ha": 365.99, "perturb_ha": 28.71}, "foret disparue": {"ha": 175.95, "perturb_ha": 0.3}, "foret recente": {"ha": 218.3, "perturb_ha": 12.92}}}}