{"code": "73017", "nom": "Apremont", "departement": "73", "region": "84", "epci": "200041010", "surface_ha": 1765.15, "foret": {"surface_ha": 1112.873, "taux_boisement": 63.047, "score": "A", "score_boisement": "A", "score_coupes": "A"}, "perturbations": {"total_ha": 1.68, "total_pixels": 168, "pixel_area_ha": 0.01, "perturb_ha_annuel": 0.217, "taux_coupe_annuel": 0.019, "observation_years": 7.75, "par_annee": {"2018": 92, "2021": 70, "2022": 6}, "annee_min": 2018, "annee_max": 2022}, "raster": {"xmin": 925979.6885419289, "xmax": 932719.6885419289, "ymin": 6490546.697153928, "ymax": 6495856.697153928, "width": 674, "height": 531, "pixel_w": 9.99999999999999, "pixel_h": 10.0}, "overlaps_zones_protegees": {"znieff1": {"overlap_pixels": 76, "overlap_ha": 0.76, "zone_pixels": 136723, "zone_ha": 1367.23, "zone_in_commune": true}, "znieff2": {"overlap_pixels": 92, "overlap_ha": 0.92, "zone_pixels": 201205, "zone_ha": 2012.05, "zone_in_commune": true}, "natura_sic": {"overlap_pixels": 0, "overlap_ha": 0.0, "zone_pixels": 3287, "zone_ha": 32.87, "zone_in_commune": true}, "natura_zps": {"overlap_pixels": 0, "overlap_ha": 0.0, "zone_pixels": 0, "zone_ha": 0.0, "zone_in_commune": false}, "reserves_naturelles": {"overlap_pixels": 0, "overlap_ha": 0.0, "zone_pixels": 0, "zone_ha": 0.0, "zone_in_commune": false}}, "overlap_foret": {"perturb_in_forest_pixels": 161, "perturb_in_forest_ha": 1.61, "perturb_outside_forest_pixels": 7, "perturb_outside_forest_ha": 0.07}, "overlap_bdforet": {"bdforet_total_ha": 1875.99, "par_couvert": {"Forêt fermée": {"ha": 1835.95, "perturb_ha": 0.92}, "Forêt ouverte": {"ha": 20.36, "perturb_ha": 0.0}, "Lande/herbacée": {"ha": 17.52, "perturb_ha": 0.0}, "Peupleraie": {"ha": 2.16, "perturb_ha": 0.48}}, "par_type": {"Formation herbacée": {"ha": 10.04, "perturb_ha": 0.0}, "Forêt fermée conifères": {"ha": 260.82, "perturb_ha": 0.0}, "Forêt fermée feuillus": {"ha": 1143.69, "perturb_ha": 0.92}, "Forêt fermée mixte": {"ha": 431.44, "perturb_ha": 0.0}, "Forêt ouverte conifères": {"ha": 1.06, "perturb_ha": 0.0}, "Forêt ouverte feuillus": {"ha": 8.97, "perturb_ha": 0.0}, "Forêt ouverte mixte": {"ha": 10.33, "perturb_ha": 0.0}, "Lande": {"ha": 7.48, "perturb_ha": 0.0}, "Peupleraie": {"ha": 2.16, "perturb_ha": 0.48}}, "par_essence": {"Formation herbacée": {"ha": 10.04, "perturb_ha": 0.0}, "Forêt fermée de feuillus purs en îlots": {"ha": 22.44, "perturb_ha": 0.0}, "Forêt fermée de hêtre pur": {"ha": 139.08, "perturb_ha": 0.0}, "Forêt fermée de pin sylvestre pur": {"ha": 46.01, "perturb_ha": 0.0}, "Forêt fermée de sapin ou épicéa": {"ha": 130.23, "perturb_ha": 0.0}, "Forêt fermée dun autre conifère pur autre que pin ": {"ha": 73.25, "perturb_ha": 0.0}, "Forêt fermée à mélange de conifères": {"ha": 11.33, "perturb_ha": 0.0}, "Forêt fermée à mélange de conifères prépondérants et feuillus": {"ha": 302.9, "perturb_ha": 0.0}, "Forêt fermée à mélange de feuillus": {"ha": 982.17, "perturb_ha": 0.92}, "Forêt fermée à mélange de feuillus prépondérants et conifères": {"ha": 128.54, "perturb_ha": 0.0}, "Forêt ouverte de conifères purs": {"ha": 1.06, "perturb_ha": 0.0}, "Forêt ouverte de feuillus purs": {"ha": 8.97, "perturb_ha": 0.0}, "Forêt ouverte à mélange de feuillus et conifères": {"ha": 10.33, "perturb_ha": 0.0}, "Lande": {"ha": 7.48, "perturb_ha": 0.0}, "Peupleraie": {"ha": 2.16, "perturb_ha": 0.48}}, "perturb_in_bdforet_ha": 1.4}, "population": {"population": 972, "densite_hab_km2": 55.1}, "forets_anciennes": {"surface_ha": 1094.63, "taux_foret_ancienne": 62.294, "perturb_in_ancienne_ha": 1.4, "perturb_in_ancienne_pct": 83.333, "par_nature": {"foret recente": {"ha": 1094.63, "perturb_ha": 1.4}}}}