{"code": "76312", "nom": "Gournay-en-Bray", "departement": "76", "region": "28", "epci": "200069730", "surface_ha": 1036.425, "foret": {"surface_ha": 50.635, "taux_boisement": 4.886, "score": "E", "score_boisement": "E", "score_coupes": "A"}, "perturbations": {"total_ha": 0.39, "total_pixels": 39, "pixel_area_ha": 0.01, "perturb_ha_annuel": 0.05, "taux_coupe_annuel": 0.099, "observation_years": 7.75, "par_annee": {"2019": 21, "2025": 18}, "annee_min": 2019, "annee_max": 2025}, "raster": {"xmin": 604439.6885419292, "xmax": 609499.6885419292, "ymin": 6928436.697153928, "ymax": 6934576.697153928, "width": 506, "height": 614, "pixel_w": 9.99999999999999, "pixel_h": 10.0}, "overlaps_zones_protegees": {"znieff1": {"overlap_pixels": 0, "overlap_ha": 0.0, "zone_pixels": 29213, "zone_ha": 292.13, "zone_in_commune": true}, "znieff2": {"overlap_pixels": 18, "overlap_ha": 0.18, "zone_pixels": 161315, "zone_ha": 1613.15, "zone_in_commune": true}, "natura_sic": {"overlap_pixels": 0, "overlap_ha": 0.0, "zone_pixels": 47158, "zone_ha": 471.58, "zone_in_commune": true}, "natura_zps": {"overlap_pixels": 0, "overlap_ha": 0.0, "zone_pixels": 0, "zone_ha": 0.0, "zone_in_commune": false}, "reserves_naturelles": {"overlap_pixels": 0, "overlap_ha": 0.0, "zone_pixels": 0, "zone_ha": 0.0, "zone_in_commune": false}}, "overlap_foret": {"perturb_in_forest_pixels": 23, "perturb_in_forest_ha": 0.23, "perturb_outside_forest_pixels": 16, "perturb_outside_forest_ha": 0.16}, "overlap_bdforet": {"bdforet_total_ha": 122.74, "bdforet_par_type": {"Forêt fermée feuillus": {"pixels": 6465, "ha": 64.65, "perturb_pixels": 39, "perturb_ha": 0.39}, "Lande": {"pixels": 3978, "ha": 39.78, "perturb_pixels": 0, "perturb_ha": 0.0}, "Peupleraie": {"pixels": 1428, "ha": 14.28, "perturb_pixels": 0, "perturb_ha": 0.0}, "Forêt fermée mixte": {"pixels": 308, "ha": 3.08, "perturb_pixels": 0, "perturb_ha": 0.0}, "Forêt fermée conifères": {"pixels": 95, "ha": 0.95, "perturb_pixels": 0, "perturb_ha": 0.0}}, "perturb_in_bdforet_pixels": 39, "perturb_in_bdforet_ha": 0.39}}