{"code": "76386", "nom": "Limpiville", "departement": "76", "region": "28", "epci": "200069821", "surface_ha": 422.571, "foret": {"surface_ha": 65.926, "taux_boisement": 15.601, "score": "D", "score_boisement": "D", "score_coupes": "D"}, "perturbations": {"total_ha": 3.03, "total_pixels": 303, "pixel_area_ha": 0.01, "perturb_ha_annuel": 0.391, "taux_coupe_annuel": 0.593, "observation_years": 7.75, "par_annee": {"2021": 55, "2022": 73, "2023": 100, "2024": 69, "2025": 6}, "annee_min": 2021, "annee_max": 2025}, "raster": {"xmin": 517959.6885419293, "xmax": 521029.6885419293, "ymin": 6955756.697153928, "ymax": 6958276.697153928, "width": 307, "height": 252, "pixel_w": 9.99999999999999, "pixel_h": 10.0}, "overlaps_zones_protegees": {"znieff1": {"overlap_pixels": 0, "overlap_ha": 0.0, "zone_pixels": 0, "zone_ha": 0.0, "zone_in_commune": false}, "znieff2": {"overlap_pixels": 302, "overlap_ha": 3.02, "zone_pixels": 24315, "zone_ha": 243.15, "zone_in_commune": true}, "natura_sic": {"overlap_pixels": 0, "overlap_ha": 0.0, "zone_pixels": 0, "zone_ha": 0.0, "zone_in_commune": false}, "natura_zps": {"overlap_pixels": 0, "overlap_ha": 0.0, "zone_pixels": 0, "zone_ha": 0.0, "zone_in_commune": false}, "reserves_naturelles": {"overlap_pixels": 0, "overlap_ha": 0.0, "zone_pixels": 0, "zone_ha": 0.0, "zone_in_commune": false}}, "overlap_foret": {"perturb_in_forest_pixels": 289, "perturb_in_forest_ha": 2.89, "perturb_outside_forest_pixels": 14, "perturb_outside_forest_ha": 0.14}, "overlap_bdforet": {"bdforet_total_ha": 109.84, "bdforet_par_type": {"Forêt ouverte feuillus": {"pixels": 53, "ha": 0.53, "perturb_pixels": 0, "perturb_ha": 0.0}, "Forêt fermée feuillus": {"pixels": 7765, "ha": 77.65, "perturb_pixels": 297, "perturb_ha": 2.97}, "Forêt ouverte conifères": {"pixels": 358, "ha": 3.58, "perturb_pixels": 0, "perturb_ha": 0.0}, "Lande": {"pixels": 839, "ha": 8.39, "perturb_pixels": 0, "perturb_ha": 0.0}, "Forêt fermée sans couvert arboré": {"pixels": 386, "ha": 3.86, "perturb_pixels": 0, "perturb_ha": 0.0}, "Forêt fermée conifères": {"pixels": 1583, "ha": 15.83, "perturb_pixels": 0, "perturb_ha": 0.0}}, "perturb_in_bdforet_pixels": 297, "perturb_in_bdforet_ha": 2.97}}