{"code": "77052", "nom": "Bréau", "departement": "77", "region": "11", "epci": "247700701", "surface_ha": 132.672, "foret": {"surface_ha": 55.899, "taux_boisement": 42.133, "score": "B", "score_boisement": "B", "score_coupes": "A"}, "perturbations": {"total_ha": 0.0, "total_pixels": 0, "pixel_area_ha": 0.01, "perturb_ha_annuel": 0.0, "taux_coupe_annuel": 0.0, "observation_years": 7.75, "par_annee": {}, "annee_min": null, "annee_max": null}, "raster": {"xmin": 690429.6885419291, "xmax": 691929.6885419291, "ymin": 6827756.697153928, "ymax": 6829336.697153928, "width": 150, "height": 158, "pixel_w": 9.99999999999999, "pixel_h": 10.0}, "overlaps_zones_protegees": {"znieff1": {"overlap_pixels": 0, "overlap_ha": 0.0, "zone_pixels": 0, "zone_ha": 0.0, "zone_in_commune": false}, "znieff2": {"overlap_pixels": 0, "overlap_ha": 0.0, "zone_pixels": 0, "zone_ha": 0.0, "zone_in_commune": false}, "natura_sic": {"overlap_pixels": 0, "overlap_ha": 0.0, "zone_pixels": 0, "zone_ha": 0.0, "zone_in_commune": false}, "natura_zps": {"overlap_pixels": 0, "overlap_ha": 0.0, "zone_pixels": 0, "zone_ha": 0.0, "zone_in_commune": false}, "reserves_naturelles": {"overlap_pixels": 0, "overlap_ha": 0.0, "zone_pixels": 0, "zone_ha": 0.0, "zone_in_commune": false}}, "overlap_foret": {"perturb_in_forest_pixels": 0, "perturb_in_forest_ha": 0.0, "perturb_outside_forest_pixels": 0, "perturb_outside_forest_ha": 0.0}, "overlap_bdforet": {"bdforet_total_ha": 113.07, "bdforet_par_type": {"Forêt fermée feuillus": {"pixels": 11307, "ha": 113.07, "perturb_pixels": 0, "perturb_ha": 0.0}}, "perturb_in_bdforet_pixels": 0, "perturb_in_bdforet_ha": 0.0}}